json_torch_models/__init__.py
json_torch_models/model.py
json_torch_models/model_factory.py
json_torch_models/utils.py
json_torch_models/modules/__init__.py
json_torch_models/modules/default_modules.py
json_torch_models-1.0.2.dist-info/LICENSE
json_torch_models-1.0.2.dist-info/METADATA
json_torch_models-1.0.2.dist-info/WHEEL
json_torch_models-1.0.2.dist-info/top_level.txt
json_torch_models-1.0.2.dist-info/RECORD
